sandy/__init__.py
sandy/constants.py
sandy/cov.py
sandy/decay.py
sandy/edistr.py
sandy/endf6.py
sandy/energy_grids.py
sandy/errorr.py
sandy/functions.py
sandy/fy.py
sandy/gendf.py
sandy/gls.py
sandy/libraries.py
sandy/lpc.py
sandy/njoy.py
sandy/pert.py
sandy/records.py
sandy/samples.py
sandy/sampling.py
sandy/settings.py
sandy/shared.py
sandy/spectra.py
sandy/tools.py
sandy/tsl.py
sandy/utils.py
sandy/xs.py
sandy/zam.py
sandy/aleph2/__init__.py
sandy/aleph2/fy_output.py
sandy/aleph2/matrix_output.py
sandy/aleph2/output_file.py
sandy/aleph2/xs_output.py
sandy/aleph2/xsfile.py
sandy/appendix/chain_yields/appendix A.txt
sandy/appendix/chain_yields/appendix B.txt
sandy/appendix/chain_yields/appendix C.txt
sandy/appendix/chain_yields/appendix D.txt
sandy/appendix/chain_yields/appendix E.txt
sandy/appendix/chain_yields/appendix F.txt
sandy/appendix/decay_data/rdd.endfb_71
sandy/appendix/decay_data/rdd.endfb_80
sandy/appendix/decay_data/rdd.jeff_311
sandy/appendix/decay_data/rdd.jeff_33
sandy/appendix/decay_data/rdd.jendl_40u
sandy/appendix/fission_yields/jeff-4t3_cea_pu9_cons_28-09-2023.stn
sandy/appendix/fission_yields/jeff-4t3_cea_pu9th_cons_28-09-2023_ind_corr
sandy/appendix/fission_yields/mixt_cea-jeff33_u_235_th_eval_c1.stn
sandy/appendix/fission_yields/mixt_cea-jeff33_u_235_th_ind_corr_mat_c1
sandy/appendix/fission_yields/mixt_cea-jeff33_u_235_th_ind_cov_mat_c1
sandy/mcnp/__init__.py
sandy/mcnp/mctal.py
sandy/mcnp/meshtal.py
sandy/mcnp/output_file.py
sandy/sections/__init__.py
sandy/sections/mf1.py
sandy/sections/mf10.py
sandy/sections/mf2.py
sandy/sections/mf3.py
sandy/sections/mf31.py
sandy/sections/mf32.py
sandy/sections/mf33.py
sandy/sections/mf34.py
sandy/sections/mf35.py
sandy/sections/mf4.py
sandy/sections/mf40.py
sandy/sections/mf5.py
sandy/sections/mf6.py
sandy/sections/mf7.py
sandy/sections/mf8.py
sandy/sections/mf9.py
sandy-1.1.0.dist-info/licenses/LICENSE
sandy-1.1.0.dist-info/METADATA
sandy-1.1.0.dist-info/WHEEL
sandy-1.1.0.dist-info/top_level.txt
sandy-1.1.0.dist-info/RECORD
