Metadata-Version: 2.4
Name: sandy
Version: 1.1.0
Summary: SANDY: sampling of nuclear data and uncertainty
Home-page: https://github.com/luca-fiorito-11/sandy
Author: Luca Fiorito
Author-email: lucafiorito.11@gmail.com
Classifier: Development Status :: 4 - Beta
Classifier: Programming Language :: Python :: 3
Requires-Python: >=3.7
License-File: LICENSE
Requires-Dist: numpy
Requires-Dist: scipy
Requires-Dist: pandas
Requires-Dist: pyyaml
Requires-Dist: openpyxl
Provides-Extra: test
Requires-Dist: numpydoc; extra == "test"
Requires-Dist: nbval; extra == "test"
Requires-Dist: codecov; extra == "test"
Requires-Dist: coveralls; extra == "test"
Requires-Dist: pytest-cov; extra == "test"
Provides-Extra: notebook
Requires-Dist: jupyterlab; extra == "notebook"
Requires-Dist: notebook; extra == "notebook"
Requires-Dist: matplotlib; extra == "notebook"
Requires-Dist: seaborn; extra == "notebook"
Requires-Dist: scikit-learn; extra == "notebook"
Requires-Dist: serpentTools; extra == "notebook"
Provides-Extra: doc
Requires-Dist: sphinx; extra == "doc"
Requires-Dist: sphinx_rtd_theme; extra == "doc"
Dynamic: license-file
